hjreborn/__init__.py
hjreborn/main.py
hjreborn/config/__init__.py
hjreborn/config/core.py
hjreborn/core/__init__.py
hjreborn/core/config.py
hjreborn/core/judger.py
hjreborn/core/problem.py
hjreborn/core/problem_validator.py
hjreborn/core/run.py
hjreborn/core/signals.py
hjreborn/frontend/__init__.py
hjreborn/frontend/judge.py
hjreborn/frontend/problen_maker.py
hjreborn/frontend/utils.py
hjreborn/i18n/__init__.py
hjreborn/i18n/en_US.py
hjreborn/i18n/zh_CN.py
hjreborn-0.1.3.dist-info/LICENSE
hjreborn-0.1.3.dist-info/METADATA
hjreborn-0.1.3.dist-info/WHEEL
hjreborn-0.1.3.dist-info/entry_points.txt
hjreborn-0.1.3.dist-info/top_level.txt
hjreborn-0.1.3.dist-info/RECORD
